src/pc_update.v
//=========================================
// pc_update.v
//=========================================

module pc_update (
    input wire [15:0] pc,
    input wire [15:0] imm,
    input wire        zero,
    input wire        branch,
    input wire        jump,
    input wire [31:0] instruction,
    input wire [15:0] target_address,
    output reg [15:0] next_pc
);
    always @(*) begin
        if (jump)
            next_pc = target_address;
        else if (branch && zero)
            next_pc = pc + imm;
        else
            next_pc = pc + 1;
    end
endmodule

src/memory.v
//=========================================
// memory.v
//=========================================

module memory (
    input wire clk,
    input wire [15:0] addr,
    input wire [15:0] data_in,
    input wire we,
    output reg [15:0] data_out
);
    reg [15:0] mem [0:255];

    always @(posedge clk) begin
        if (we) begin
         mem[addr] <= data_in;
    end
    end
    always @(*)begin
         data_out = mem[addr];
    end
endmodule

src/alu.v
//=========================================
// alu.v
//=========================================

module alu (
    input wire [15:0] a,
    input wire [15:0] b,
    input wire [3:0] opcode,
    output reg [15:0] result,
    output reg zero
);
    always @(*) begin
        case (opcode)
            4'b0000: result = a + b;
            4'b0001: result = a - b;
            4'b0010: result = a * b;
            4'b0011: result = a / b;
            4'b0100: result = a % b;
            4'b0101: result = a & b;
            4'b0110: result = a | b;
            4'b0111: result = ~a;
            4'b1000: result = a << 1;
            4'b1001: result = a >> 1;
            4'b1010: result = a >>> 1;
            4'b1011: result = (a < b) ? 16'd1 : 16'd0;
            default: result = 16'd0;
        endcase
        zero = (result == 16'd0);
    end
endmodule

src/imm_gen.v
//=========================================
// imm_gen.v
//=========================================

module imm_gen (
    input wire [31:0] instruction,
    output reg [15:0] imm_out
);
    wire [4:0] opcode = instruction[31:27];
     always @(*) begin
        case (opcode)
            5'b01110,//ld, st
            5'b01111: // JMP: extract 16-bit immediate
                imm_out = instruction[19:4];
            //branch
            5'b0000,
            5'b10001,
            5'b10010,
            5'b10011,
            5'b10100:
                imm_out = instruction[26:11];
            default:
                imm_out = instruction[19:4]; // Default for others
        endcase
    end
endmodule

src/register_file.v
//=========================================
// register_file.v
//=========================================

module register_file (
    input wire clk,
    input wire reset,
    input wire [3:0] read_addr1,
    input wire [3:0] read_addr2,
    input wire [3:0] write_addr,
    input wire [15:0] write_data,
    input wire write_enable,
    output reg [15:0] read_data1,
    output reg [15:0] read_data2
);
    reg [15:0] registers [0:15];

    always @(posedge clk or posedge reset) begin  
    	if (reset) begin
            registers[0] <= 16'd0;
            registers[1] <= 16'd0;
            registers[2] <= 16'd0;
            registers[3] <= 16'd0;
            registers[4] <= 16'd0;
            registers[5] <= 16'd0;
            registers[6] <= 16'd0;
            registers[7] <= 16'd0;
            registers[8] <= 16'd0;
            registers[9] <= 16'd0;
            registers[10] <= 16'd0;
            registers[11] <= 16'd0;
            registers[12] <= 16'd0;
            registers[13] <= 16'd0;
            registers[14] <= 16'd0;
            registers[15] <= 16'd0;
            
    	end else if (write_enable) begin
        	registers[write_addr] <= write_data;
    	end
    end

    always @(*) begin
        read_data1 = registers[read_addr1];
        read_data2 = registers[read_addr2];
    end
endmodule

src/control_unit.v
//=========================================
// control_unit.v
//=========================================

module control_unit (
    input wire [31:0] instruction,
    output reg [3:0] alu_op,
    output reg alu_src,
    output reg reg_write,
    output reg mem_read,
    output reg mem_write,
    output reg mem_to_reg,
    output reg branch,
    output reg jump
);
    wire [4:0] opcode = instruction[31:27];
    always @(*) begin
        alu_op = 4'b0000;
        alu_src = 1'b0;
        reg_write = 1'b0;
        mem_read = 1'b0;
        mem_write = 1'b0;
        mem_to_reg = 1'b0;
        branch = 1'b0;
        jump = 1'b0;

        case (opcode)
            5'b00000: begin // ADD
                alu_op = 4'b0000;
                reg_write = 1'b1;
                alu_src = 1'b0;
            end
            5'b00001: begin // SUB
                alu_op = 4'b0001;
                reg_write = 1'b1;
                alu_src = 1'b0;
            end
            5'b00010: begin // MUL
                alu_op = 4'b0010;
                reg_write = 1'b1;
                alu_src = 1'b0;
            end
            5'b00011: begin // DIV
                alu_op = 4'b0011;
                reg_write = 1'b1;
                alu_src = 1'b0;
            end
            5'b00100: begin // MOD
                alu_op = 4'b0100;
                reg_write = 1'b1;
                alu_src = 1'b0;
            end
            5'b00101: begin // CMP
                alu_op = 4'b1011;
                alu_src = 1'b0;
            end
            5'b00110: begin // AND
                alu_op = 4'b0101;
                reg_write = 1'b1;
                alu_src = 1'b0;
            end
            5'b00111: begin // OR
                alu_op = 4'b0110;
                reg_write = 1'b1;
                alu_src = 1'b0;
            end
            5'b01000: begin // NOT
                alu_op = 4'b0111;
                reg_write = 1'b1;
                alu_src = 1'b0;
            end
            5'b01001: begin // MOV
                alu_op = 4'b0000;
                reg_write = 1'b1;
                alu_src = 1'b1;
            end
            5'b01010: begin // LSL
                alu_op = 4'b1000;
                reg_write = 1'b1;
                alu_src = 1'b0;
            end
            5'b01011: begin // LSR
                alu_op = 4'b1001;
                reg_write = 1'b1;
                alu_src = 1'b0;
            end
            5'b01100: begin // ASR
                alu_op = 4'b1010;
                alu_src = 1'b0;
                reg_write = 1'b1;
            end
            5'b01101: begin // NOP
                //NO OPERATION
            end
            5'b01110: begin // LD
                alu_op = 4'b0000;
                alu_src = 1'b1;
                mem_read = 1'b1;
                mem_to_reg = 1'b1;
                reg_write = 1'b1;
            end
            5'b01111: begin // ST
            	alu_op = 4'b0000;
                alu_src = 1'b1;
                mem_write = 1'b1;
            end
            5'b01111: begin // BEQ
            	alu_op = 4'b0001;
                alu_src = 1'b0;
                branch = 1'b1;
            end
            5'b10001: begin // BGT
            	alu_op = 4'b0001;
                alu_src = 1'b0;
                branch = 1'b1;
            end
            5'b10010: begin // B
            	jump =1'b1;

            end
            5'b10011: begin // CALL
            	jump =1'b1;
                reg_write = 1'b1;
            end
            5'b10100: begin // RET
            	jump = 1'b1;
            end
        endcase
    end
endmodule

src/instr_mem.v
//=========================================
// instr_mem.v (ROM)
//=========================================

module instr_mem (
    input wire [15:0] addr,
    output wire [31:0] data_out
);
    reg [31:0] mem [0:255];
    integer i;
    initial begin
        for(i =0; i< 256; i= i+1) begin
            mem[i] = 32'h0000_0000;
        end

    	$display("Loading instructions...");
        $readmemh("program.hex", mem);
    end

    assign data_out = mem[addr];
endmodule

src/processor.v
//=========================================
// processor.v (TOP LEVEL)
//=========================================

module processor (
    input wire clk,
    input wire reset
);
    // Program Counter
    reg [15:0] pc;
    wire [15:0] next_pc;

    // Instruction
    wire [31:0] instruction;

    instr_mem instr_mem_inst (
        .addr(pc),
        .data_out(instruction)
    );
    // Control signals
    wire [3:0] alu_op;
    wire       alu_src,reg_write, mem_read, mem_write, mem_to_reg, branch, jump;
    control_unit cu (
        .instruction(instruction),
        .alu_op(alu_op),
        .alu_src(alu_src),
        .reg_write(reg_write),
        .mem_read(mem_read),
        .mem_write(mem_write),
        .mem_to_reg(mem_to_reg),
        .branch(branch),
        .jump(jump)
    );

    // Register File
    wire [3:0] rd = instruction[25:22];
    wire [3:0] rs1 = instruction[21:18];
    wire [3:0] rs2 = instruction[17:14];
    wire [15:0] write_data, rf_out1, rf_out2;
    register_file rf (
        .clk(clk),
        .reset(reset),
        .read_addr1(rs1),
        .read_addr2(rs2),
        .write_addr(rd),
        .write_data(write_data),
        .write_enable(reg_write),
        .read_data1(rf_out1),
        .read_data2(rf_out2)
    );

    //Immediate generator
    wire[15:0] imm;
    imm_gen ig(
        .instruction(instruction),
        .imm_out(imm)
    );

    // ALU
    wire [15:0] alu_b = alu_src ? imm : rf_out2; 
    wire [15:0] alu_result;
    wire        zero_flag;
    alu alu_inst (
        .a(rf_out1),
        .b(alu_b),
        .opcode(alu_op),
        .result(alu_result),
        .zero(zero_flag)
    );

    // Data Memory
    wire [15:0] mem_data;
    memory data_mem (
        .clk(clk),
        .addr(alu_result),
        .data_in(rf_out2),
        .we(mem_write),
        .data_out(mem_data)
    );

    // Write-back mux
    assign write_data = mem_to_reg ? mem_data : alu_result;

    // PC update logic
    pc_update pcupd (
        .pc(pc),
        .imm(imm),
        .zero(zero_flag),
        .branch(branch),
        .jump(jump),
        .instruction(instruction),
        .target_address(alu_result),
        .next_pc(next_pc)
    );

    // PC Register
    always @(posedge clk or posedge reset) begin
        if (reset)
            pc <= 16'h0000;
        else
            pc <= next_pc;
    end

endmodule

testbench/processor_tb.v
//=========================================
// tb_processor.v - Testbench for processor
//=========================================
`timescale 1ns / 1ps

module tb_processor;
    reg clk = 0;
    reg reset = 0;

    // Instantiate the processor
    processor uut (
        .clk(clk),
        .reset(reset)
    );

    // Clock gen
    initial forever #5 clk = ~clk;

    // Proper reset pulse
    initial begin
        #1  reset = 1;
        #19 reset = 0;
    end

    // Wave dump & finish
    initial begin
        $dumpfile("processor.vcd");
        $dumpvars(0, tb_processor);
        $display("Starting simulation...");
        reset = 1;
        #10;
        reset = 0; 
        #1000;
        $finish;
    end

    // --- NOW at module scope, not inside another initial ---
    // 1) Print header once
    initial begin
        $display("Time\tPC\tInstr\t         R0\t R1\t R2\t R3\t R4\t R5\t R6\t R7\t R8\t R9\t R10\t R11\t R12\t R13\t R14\t   R15");
    end

    // 2) On each clock edge, print a row
    always @(posedge clk) begin
        $display("%0t\t%h\t%h\t%h\t%h\t%h\t%h\t%h\t%h\t%h\t%h\t%h\t%h\t%h\t%h\t%h\t%h\t%h\t%d",
            $time,
            uut.pc,
            uut.instr_mem_inst.mem[uut.pc],
            uut.rf.registers[0],
            uut.rf.registers[1],
            uut.rf.registers[2],
            uut.rf.registers[3],
            uut.rf.registers[4],
            uut.rf.registers[5],
            uut.rf.registers[6],
            uut.rf.registers[7],
            uut.rf.registers[8],
            uut.rf.registers[9],
            uut.rf.registers[10],
            uut.rf.registers[11],
            uut.rf.registers[12],
            uut.rf.registers[13],
            uut.rf.registers[14],
            uut.rf.registers[15]
        );
    end

    // After 1000 ns, report final status and registers, then finish
    initial begin
        #1000;  // match your simulation length
        $display("\n=== Simulation complete: program.hex executed successfully ===");
        $display("Final register file contents:");
        $display("R0:%h, R1:%h, R2:%h, R3:%h, R4:%h,R5:%h, R6:%h, R7:%h, R8:%h, R9:%h, R10:%h, R11:%h, R12:%h, R13:%h, R14:%h, R15:%h",
        uut.rf.registers[0],
        uut.rf.registers[1],
        uut.rf.registers[2],
        uut.rf.registers[3],
        uut.rf.registers[4],
        uut.rf.registers[5],
        uut.rf.registers[6],
        uut.rf.registers[7],
        uut.rf.registers[8],
        uut.rf.registers[9],
        uut.rf.registers[10],
        uut.rf.registers[11],
        uut.rf.registers[12],
        uut.rf.registers[13],
        uut.rf.registers[14],
        uut.rf.registers[15]
        );
        $finish;
    end


endmodule

sim/processor.vcd
$date
	Wed Apr 23 04:03:39 2025
$end
$version
	Icarus Verilog
$end
$timescale
	1ps
$end
$scope module tb_processor $end
$var reg 1 ! clk $end
$var reg 1 " reset $end
$scope module uut $end
$var wire 1 ! clk $end
$var wire 1 " reset $end
$var wire 1 # zero_flag $end
$var wire 16 $ write_data [15:0] $end
$var wire 4 % rs2 [3:0] $end
$var wire 4 & rs1 [3:0] $end
$var wire 16 ' rf_out2 [15:0] $end
$var wire 16 ( rf_out1 [15:0] $end
$var wire 1 ) reg_write $end
$var wire 4 * rd [3:0] $end
$var wire 16 + next_pc [15:0] $end
$var wire 1 , mem_write $end
$var wire 1 - mem_to_reg $end
$var wire 1 . mem_read $end
$var wire 16 / mem_data [15:0] $end
$var wire 1 0 jump $end
$var wire 32 1 instruction [31:0] $end
$var wire 16 2 imm [15:0] $end
$var wire 1 3 branch $end
$var wire 1 4 alu_src $end
$var wire 16 5 alu_result [15:0] $end
$var wire 4 6 alu_op [3:0] $end
$var wire 16 7 alu_b [15:0] $end
$var reg 16 8 pc [15:0] $end
$scope module alu_inst $end
$var wire 16 9 b [15:0] $end
$var wire 4 : opcode [3:0] $end
$var wire 16 ; a [15:0] $end
$var reg 16 < result [15:0] $end
$var reg 1 # zero $end
$upscope $end
$scope module cu $end
$var wire 5 = opcode [4:0] $end
$var wire 32 > instruction [31:0] $end
$var reg 4 ? alu_op [3:0] $end
$var reg 1 4 alu_src $end
$var reg 1 3 branch $end
$var reg 1 0 jump $end
$var reg 1 . mem_read $end
$var reg 1 - mem_to_reg $end
$var reg 1 , mem_write $end
$var reg 1 ) reg_write $end
$upscope $end
$scope module data_mem $end
$var wire 16 @ addr [15:0] $end
$var wire 1 ! clk $end
$var wire 1 , we $end
$var wire 16 A data_in [15:0] $end
$var reg 16 B data_out [15:0] $end
$upscope $end
$scope module ig $end
$var wire 5 C opcode [4:0] $end
$var wire 32 D instruction [31:0] $end
$var reg 16 E imm_out [15:0] $end
$upscope $end
$scope module instr_mem_inst $end
$var wire 16 F addr [15:0] $end
$var wire 32 G data_out [31:0] $end
$var integer 32 H i [31:0] $end
$upscope $end
$scope module pcupd $end
$var wire 1 3 branch $end
$var wire 16 I imm [15:0] $end
$var wire 32 J instruction [31:0] $end
$var wire 1 0 jump $end
$var wire 16 K pc [15:0] $end
$var wire 16 L target_address [15:0] $end
$var wire 1 # zero $end
$var reg 16 M next_pc [15:0] $end
$upscope $end
$scope module rf $end
$var wire 1 ! clk $end
$var wire 4 N read_addr1 [3:0] $end
$var wire 4 O read_addr2 [3:0] $end
$var wire 1 " reset $end
$var wire 4 P write_addr [3:0] $end
$var wire 16 Q write_data [15:0] $end
$var wire 1 ) write_enable $end
$var reg 16 R read_data1 [15:0] $end
$var reg 16 S read_data2 [15:0] $end
$upscope $end
$upscope $end
$upscope $end
$enddefinitions $end
#0
$dumpvars
b0 S
b0 R
b100 Q
b10 P
b0 O
b0 N
b1 M
b100 L
b0 K
b1001100100000000000000001000000 J
b100 I
b100000000 H
b1001100100000000000000001000000 G
b0 F
b100 E
b1001100100000000000000001000000 D
b1001 C
bx B
b0 A
b100 @
b0 ?
b1001100100000000000000001000000 >
b1001 =
b100 <
b0 ;
b0 :
b100 9
b0 8
b100 7
b0 6
b100 5
14
03
b100 2
b1001100100000000000000001000000 1
00
bx /
0.
0-
0,
b1 +
b10 *
1)
b0 (
b0 '
b0 &
b0 %
b100 $
0#
1"
0!
$end
#5000
1!
#10000
0!
0"
#15000
b10 $
b10 Q
b10 5
b10 <
b10 @
b10 L
b10 7
b10 9
b11 *
b11 P
b10 2
b10 E
b10 I
b10 +
b10 M
b1001100110000000000000000100000 1
b1001100110000000000000000100000 >
b1001100110000000000000000100000 D
b1001100110000000000000000100000 G
b1001100110000000000000000100000 J
b1 8
b1 F
b1 K
1!
#20000
0!
#25000
b1000 $
b1000 Q
b1000 5
b1000 <
b1000 @
b1000 L
b10 6
b10 :
b10 ?
1)
04
b10 '
b10 A
b10 S
b100 (
b100 ;
b100 R
b10 7
b10 9
b10 C
b10 =
b11 %
b11 O
b10 &
b10 N
b100 *
b100 P
b1000110000000000 2
b1000110000000000 E
b1000110000000000 I
b11 +
b11 M
b10001000010001100000000000000 1
b10001000010001100000000000000 >
b10001000010001100000000000000 D
b10001000010001100000000000000 G
b10001000010001100000000000000 J
b10 8
b10 F
b10 K
1!
#30000
0!
#35000
1#
b0 $
b0 Q
b0 7
b0 9
b0 5
b0 <
b0 @
b0 L
1)
b0 6
b0 :
b0 ?
b0 '
b0 A
b0 S
b0 (
b0 ;
b0 R
b0 C
b0 =
b0 %
b0 O
b0 &
b0 N
b0 *
b0 P
b0 2
b0 E
b0 I
b100 +
b100 M
b0 1
b0 >
b0 D
b0 G
b0 J
b11 8
b11 F
b11 K
1!
#40000
0!
#45000
b101 +
b101 M
b100 8
b100 F
b100 K
1!
#50000
0!
#55000
b110 +
b110 M
b101 8
b101 F
b101 K
1!
#60000
0!
#65000
b111 +
b111 M
b110 8
b110 F
b110 K
1!
#70000
0!
#75000
b1000 +
b1000 M
b111 8
b111 F
b111 K
1!
#80000
0!
#85000
b1001 +
b1001 M
b1000 8
b1000 F
b1000 K
1!
#90000
0!
#95000
b1010 +
b1010 M
b1001 8
b1001 F
b1001 K
1!
#100000
0!
#105000
b1011 +
b1011 M
b1010 8
b1010 F
b1010 K
1!
#110000
0!
#115000
b1100 +
b1100 M
b1011 8
b1011 F
b1011 K
1!
#120000
0!
#125000
b1101 +
b1101 M
b1100 8
b1100 F
b1100 K
1!
#130000
0!
#135000
b1110 +
b1110 M
b1101 8
b1101 F
b1101 K
1!
#140000
0!
#145000
b1111 +
b1111 M
b1110 8
b1110 F
b1110 K
1!
#150000
0!
#155000
b10000 +
b10000 M
b1111 8
b1111 F
b1111 K
1!
#160000
0!
#165000
b10001 +
b10001 M
b10000 8
b10000 F
b10000 K
1!
#170000
0!
#175000
b10010 +
b10010 M
b10001 8
b10001 F
b10001 K
1!
#180000
0!
#185000
b10011 +
b10011 M
b10010 8
b10010 F
b10010 K
1!
#190000
0!
#195000
b10100 +
b10100 M
b10011 8
b10011 F
b10011 K
1!
#200000
0!
#205000
b10101 +
b10101 M
b10100 8
b10100 F
b10100 K
1!
#210000
0!
#215000
b10110 +
b10110 M
b10101 8
b10101 F
b10101 K
1!
#220000
0!
#225000
b10111 +
b10111 M
b10110 8
b10110 F
b10110 K
1!
#230000
0!
#235000
b11000 +
b11000 M
b10111 8
b10111 F
b10111 K
1!
#240000
0!
#245000
b11001 +
b11001 M
b11000 8
b11000 F
b11000 K
1!
#250000
0!
#255000
b11010 +
b11010 M
b11001 8
b11001 F
b11001 K
1!
#260000
0!
#265000
b11011 +
b11011 M
b11010 8
b11010 F
b11010 K
1!
#270000
0!
#275000
b11100 +
b11100 M
b11011 8
b11011 F
b11011 K
1!
#280000
0!
#285000
b11101 +
b11101 M
b11100 8
b11100 F
b11100 K
1!
#290000
0!
#295000
b11110 +
b11110 M
b11101 8
b11101 F
b11101 K
1!
#300000
0!
#305000
b11111 +
b11111 M
b11110 8
b11110 F
b11110 K
1!
#310000
0!
#315000
b100000 +
b100000 M
b11111 8
b11111 F
b11111 K
1!
#320000
0!
#325000
b100001 +
b100001 M
b100000 8
b100000 F
b100000 K
1!
#330000
0!
#335000
b100010 +
b100010 M
b100001 8
b100001 F
b100001 K
1!
#340000
0!
#345000
b100011 +
b100011 M
b100010 8
b100010 F
b100010 K
1!
#350000
0!
#355000
b100100 +
b100100 M
b100011 8
b100011 F
b100011 K
1!
#360000
0!
#365000
b100101 +
b100101 M
b100100 8
b100100 F
b100100 K
1!
#370000
0!
#375000
b100110 +
b100110 M
b100101 8
b100101 F
b100101 K
1!
#380000
0!
#385000
b100111 +
b100111 M
b100110 8
b100110 F
b100110 K
1!
#390000
0!
#395000
b101000 +
b101000 M
b100111 8
b100111 F
b100111 K
1!
#400000
0!
#405000
b101001 +
b101001 M
b101000 8
b101000 F
b101000 K
1!
#410000
0!
#415000
b101010 +
b101010 M
b101001 8
b101001 F
b101001 K
1!
#420000
0!
#425000
b101011 +
b101011 M
b101010 8
b101010 F
b101010 K
1!
#430000
0!
#435000
b101100 +
b101100 M
b101011 8
b101011 F
b101011 K
1!
#440000
0!
#445000
b101101 +
b101101 M
b101100 8
b101100 F
b101100 K
1!
#450000
0!
#455000
b101110 +
b101110 M
b101101 8
b101101 F
b101101 K
1!
#460000
0!
#465000
b101111 +
b101111 M
b101110 8
b101110 F
b101110 K
1!
#470000
0!
#475000
b110000 +
b110000 M
b101111 8
b101111 F
b101111 K
1!
#480000
0!
#485000
b110001 +
b110001 M
b110000 8
b110000 F
b110000 K
1!
#490000
0!
#495000
b110010 +
b110010 M
b110001 8
b110001 F
b110001 K
1!
#500000
0!
#505000
b110011 +
b110011 M
b110010 8
b110010 F
b110010 K
1!
#510000
0!
#515000
b110100 +
b110100 M
b110011 8
b110011 F
b110011 K
1!
#520000
0!
#525000
b110101 +
b110101 M
b110100 8
b110100 F
b110100 K
1!
#530000
0!
#535000
b110110 +
b110110 M
b110101 8
b110101 F
b110101 K
1!
#540000
0!
#545000
b110111 +
b110111 M
b110110 8
b110110 F
b110110 K
1!
#550000
0!
#555000
b111000 +
b111000 M
b110111 8
b110111 F
b110111 K
1!
#560000
0!
#565000
b111001 +
b111001 M
b111000 8
b111000 F
b111000 K
1!
#570000
0!
#575000
b111010 +
b111010 M
b111001 8
b111001 F
b111001 K
1!
#580000
0!
#585000
b111011 +
b111011 M
b111010 8
b111010 F
b111010 K
1!
#590000
0!
#595000
b111100 +
b111100 M
b111011 8
b111011 F
b111011 K
1!
#600000
0!
#605000
b111101 +
b111101 M
b111100 8
b111100 F
b111100 K
1!
#610000
0!
#615000
b111110 +
b111110 M
b111101 8
b111101 F
b111101 K
1!
#620000
0!
#625000
b111111 +
b111111 M
b111110 8
b111110 F
b111110 K
1!
#630000
0!
#635000
b1000000 +
b1000000 M
b111111 8
b111111 F
b111111 K
1!
#640000
0!
#645000
b1000001 +
b1000001 M
b1000000 8
b1000000 F
b1000000 K
1!
#650000
0!
#655000
b1000010 +
b1000010 M
b1000001 8
b1000001 F
b1000001 K
1!
#660000
0!
#665000
b1000011 +
b1000011 M
b1000010 8
b1000010 F
b1000010 K
1!
#670000
0!
#675000
b1000100 +
b1000100 M
b1000011 8
b1000011 F
b1000011 K
1!
#680000
0!
#685000
b1000101 +
b1000101 M
b1000100 8
b1000100 F
b1000100 K
1!
#690000
0!
#695000
b1000110 +
b1000110 M
b1000101 8
b1000101 F
b1000101 K
1!
#700000
0!
#705000
b1000111 +
b1000111 M
b1000110 8
b1000110 F
b1000110 K
1!
#710000
0!
#715000
b1001000 +
b1001000 M
b1000111 8
b1000111 F
b1000111 K
1!
#720000
0!
#725000
b1001001 +
b1001001 M
b1001000 8
b1001000 F
b1001000 K
1!
#730000
0!
#735000
b1001010 +
b1001010 M
b1001001 8
b1001001 F
b1001001 K
1!
#740000
0!
#745000
b1001011 +
b1001011 M
b1001010 8
b1001010 F
b1001010 K
1!
#750000
0!
#755000
b1001100 +
b1001100 M
b1001011 8
b1001011 F
b1001011 K
1!
#760000
0!
#765000
b1001101 +
b1001101 M
b1001100 8
b1001100 F
b1001100 K
1!
#770000
0!
#775000
b1001110 +
b1001110 M
b1001101 8
b1001101 F
b1001101 K
1!
#780000
0!
#785000
b1001111 +
b1001111 M
b1001110 8
b1001110 F
b1001110 K
1!
#790000
0!
#795000
b1010000 +
b1010000 M
b1001111 8
b1001111 F
b1001111 K
1!
#800000
0!
#805000
b1010001 +
b1010001 M
b1010000 8
b1010000 F
b1010000 K
1!
#810000
0!
#815000
b1010010 +
b1010010 M
b1010001 8
b1010001 F
b1010001 K
1!
#820000
0!
#825000
b1010011 +
b1010011 M
b1010010 8
b1010010 F
b1010010 K
1!
#830000
0!
#835000
b1010100 +
b1010100 M
b1010011 8
b1010011 F
b1010011 K
1!
#840000
0!
#845000
b1010101 +
b1010101 M
b1010100 8
b1010100 F
b1010100 K
1!
#850000
0!
#855000
b1010110 +
b1010110 M
b1010101 8
b1010101 F
b1010101 K
1!
#860000
0!
#865000
b1010111 +
b1010111 M
b1010110 8
b1010110 F
b1010110 K
1!
#870000
0!
#875000
b1011000 +
b1011000 M
b1010111 8
b1010111 F
b1010111 K
1!
#880000
0!
#885000
b1011001 +
b1011001 M
b1011000 8
b1011000 F
b1011000 K
1!
#890000
0!
#895000
b1011010 +
b1011010 M
b1011001 8
b1011001 F
b1011001 K
1!
#900000
0!
#905000
b1011011 +
b1011011 M
b1011010 8
b1011010 F
b1011010 K
1!
#910000
0!
#915000
b1011100 +
b1011100 M
b1011011 8
b1011011 F
b1011011 K
1!
#920000
0!
#925000
b1011101 +
b1011101 M
b1011100 8
b1011100 F
b1011100 K
1!
#930000
0!
#935000
b1011110 +
b1011110 M
b1011101 8
b1011101 F
b1011101 K
1!
#940000
0!
#945000
b1011111 +
b1011111 M
b1011110 8
b1011110 F
b1011110 K
1!
#950000
0!
#955000
b1100000 +
b1100000 M
b1011111 8
b1011111 F
b1011111 K
1!
#960000
0!
#965000
b1100001 +
b1100001 M
b1100000 8
b1100000 F
b1100000 K
1!
#970000
0!
#975000
b1100010 +
b1100010 M
b1100001 8
b1100001 F
b1100001 K
1!
#980000
0!
#985000
b1100011 +
b1100011 M
b1100010 8
b1100010 F
b1100010 K
1!
#990000
0!
#995000
b1100100 +
b1100100 M
b1100011 8
b1100011 F
b1100011 K
1!
